{"id":1872,"slug":"λογοθεραπευτικό-κέντρο-βούλας","title":"Λογοθεραπευτικό Κέντρο Βούλας","link":"https://okosmostoupari.gr/professional/%ce%bb%ce%bf%ce%b3%ce%bf%ce%b8%ce%b5%cf%81%ce%b1%cf%80%ce%b5%cf%85%cf%84%ce%b9%ce%ba%cf%8c-%ce%ba%ce%ad%ce%bd%cf%84%cf%81%ce%bf-%ce%b2%ce%bf%cf%8d%ce%bb%ce%b1%cf%82/","photo":"https://okosmostoupari.gr/wp-content/uploads/2023/06/Λογοθεραπευτικό-Κέντρο-Βούλας-36eca5b438cac0b972907009f2156074.jpg","categories":["Ειδικό κέντρο λόγου και έργου","Βρέφη","Ενήλικες","Έφηβοι","Παιδιά"],"contentHtml":"<p>Το ¨Λογοθεραπευτικό Κέντρο Βούλας¨ δημιουργήθηκε από άτομα με επιστημονική κατάρτιση, υπευθυνότητα και σεβασμό για παιδιά και εφήβους με προβλήματα στην ανάπτυξη.<br>\nΤο κέντρο στοχεύει στην σφαιρική αντιμετώπιση των δυσκολιών, προσαρμοσμένη στις ανάγκες κάθε ατόμου.<br>\nΗ διεπιστημονική ομάδα στελεχώνεται από Λογοθεραπευτή, Εργοθεραπευτή, Ειδικό Παιδαγωγό, Ψυχολόγο, Παιγνιοθεραπευτή και Παιδοψυχίατρο.<br>\nΣκοπός του κέντρου μας είναι:<br>\n-έγκυρη και αξιόπιστη αξιολόγηση των δυνατοτήτων του ατόμου<br>\n-πρόληψη και αντιμετώπιση των δυσκολιών<br>\n-αποτελεσματική θεραπευτική παρέμβαση<br>\n-κοινωνικοποίηση του ατόμου<br>\n-συνεργασία με εκπαιδευτικούς φορείς και οικογένεια<br>\n-παροχή ψυχολογικής υποστήριξης παιδιών και γονέων<br>\nΣτο φιλικό και πλήρως εξοπλισμένο περιβάλλον του ¨Λογοθεραπευτικού Κέντρου Βούλας¨ καλύπτεται ένα ευρύ φάσμα διαταραχών:<br>\n– προβλήματα λόγου, ομιλίας και επικοινωνίας<br>\n– ειδικές μαθησιακές δυσκολίες<br>\n– δυσλεξία<br>\n– τραυλισμός<br>\n– προβλήματα μάθησης/ κατανόησης<br>\n– νοητική υστέρηση/ σύνδρομα<br>\n– διάχυτες αναπτυξιακές διαταραχές, π.χ αυτισμός<br>\n-προβλήματα ακοής/ βαρηκοΐα<br>\n-υπερκινητικότητα<br>\n– δυσκολίες συγκέντρωσης/ διάσπαση προσοχής<br>\n– ψυχοκινητική καθυστέρηση/ διαταραχές κινητικών δεξιοτήτων<br>\n– νευρολογικές διαταραχές, π.χ εγκεφαλικά επεισόδια, κρανιοεγκεφαλικές κακώσεις.</p>\n<p>Συνεργαζόμαστε με ιατρούς όλων των ειδικοτήτων και με όλα τα ασφαλιστικά ταμεία.</p>\n<p>Επιστημονικά Υπεύθυνος<br>\nΚουράκος Γιώργος- Λογοθεραπευτής<br>\nΜέλος Δ.Σ του Συλλόγου Επιστημόνων Λογοπαθολόγων- Λογοθεραπευτών Ελλάδος</p>","address":"Βούλα","phone":"2108992093","email":"info@lkv.gr","website":"http://lkv.gr/","facebook":"https://www.facebook.com/therapeialogou","hours":null,"rating":{"average":0,"count":0},"reviews":[]}