{"id":2537,"slug":"παράρτημα-αποθεραπείας-και-αποκατάσ-2","title":"Παράρτημα Αποθεραπείας και Αποκατάστασης Παιδιών με Αναπηρία Θεσσαλονίκης «Ο Άγιος Δημήτριος»","link":"https://okosmostoupari.gr/professional/%cf%80%ce%b1%cf%81%ce%ac%cf%81%cf%84%ce%b7%ce%bc%ce%b1-%ce%b1%cf%80%ce%bf%ce%b8%ce%b5%cf%81%ce%b1%cf%80%ce%b5%ce%af%ce%b1%cf%82-%ce%ba%ce%b1%ce%b9-%ce%b1%cf%80%ce%bf%ce%ba%ce%b1%cf%84%ce%ac%cf%83-2/","photo":null,"categories":["Κέντρο αποθεραπείας & αποκατάστασης","Κέντρο ημερήσιας φροντίδας","Οικοτροφείο","Προστατευόμενο διαμέρισμα","Ενήλικες","Έφηβοι","Παιδιά"],"contentHtml":"<p>Το ΠΑΑΠΑΘ «Ο Άγιος Δημήτριος» βρίσκεται στην Πυλαία Θεσσαλονίκης και λειτουργεί από το 1973 ως δομή κλειστής περίθαλψης παιδιών με νοητική αναπηρία και κινητικές δυσκολίες ή πολλαπλές αναπηρίες, ηλικίας 2,5 και άνω. Σκοπός του παραρτήματος είναι η παροχή φροντίδας, περίθαλψης, εκπαίδευσης , απασχόλησης καθώς και λειτουργική, κοινωνική και επαγγελματική κατάρτιση και αποκατάσταση.</p>\n<p>Παρέχονται υπηρεσίες θεραπευτικών προγραμμάτων Φυσικοθεραπείας, Εργοθεραπείας, Ψυχοκοινωνικής υποστήριξης και συμβουλευτικής των οικογενειών τους. Επιπλέον λειτουργούν προγράμματα επαγγελματικής κατάρτισης, Εθελοντισμού, Άθλησης, Ευαισθητοποίησης της Κοινότητας, Διαχείρισης Ευρωπαϊκών προγραμμάτων και Επιμόρφωσης Προσωπικού.</p>\n<p>Η πορεία αποϊδρυματοποίησης του Παραρτήματος είναι μία πολυετής διαδρομή που ξεκινάει από το 2001 με τη δημιουργία προστατευμένων κατοικιών και συνεχίζεται μέχρι σήμερα.</p>\n<p>Παρέχονται υπηρεσίες κλειστής περίθαλψης (προσομοιωμένες κατοικίες – προστατευμένες κατοικίες, κατοικίες στην κοινότητα) και υπηρεσίες ανοιχτής περίθαλψης (Κέντρο Ημέρας και Φιλοξενείο)</p>","address":"Τζων Κέννεντυ 62, Πυλαία-Χορτιάτης 555 35","phone":"2313 320 100","email":"Grammateia.kkpkm@n3.syzefxis.gov.gr","website":"https://kkp-km.gr/branches/1","facebook":null,"hours":null,"rating":{"average":0,"count":0},"reviews":[]}